fianchetto_tradebot/__init__.py
fianchetto_tradebot/client/__init__.py
fianchetto_tradebot/client/client.py
fianchetto_tradebot/client/samples/__init__.py
fianchetto_tradebot/common_models/__init__.py
fianchetto_tradebot/common_models/account/__init__.py
fianchetto_tradebot/common_models/account/account.py
fianchetto_tradebot/common_models/account/account_balance.py
fianchetto_tradebot/common_models/account/brokerage_call.py
fianchetto_tradebot/common_models/account/computed_balance.py
fianchetto_tradebot/common_models/account/option_level.py
fianchetto_tradebot/common_models/account/etrade/__init__.py
fianchetto_tradebot/common_models/account/etrade/etrade_account.py
fianchetto_tradebot/common_models/account/ikbr/__init__.py
fianchetto_tradebot/common_models/account/schwab/__init__.py
fianchetto_tradebot/common_models/api/__init__.py
fianchetto_tradebot/common_models/api/request.py
fianchetto_tradebot/common_models/api/request_status.py
fianchetto_tradebot/common_models/api/response.py
fianchetto_tradebot/common_models/api/account/__init__.py
fianchetto_tradebot/common_models/api/account/get_account_balance_request.py
fianchetto_tradebot/common_models/api/account/get_account_balance_response.py
fianchetto_tradebot/common_models/api/account/get_account_request.py
fianchetto_tradebot/common_models/api/account/get_account_response.py
fianchetto_tradebot/common_models/api/account/list_accounts_request.py
fianchetto_tradebot/common_models/api/account/list_accounts_response.py
fianchetto_tradebot/common_models/api/finance/__init__.py
fianchetto_tradebot/common_models/api/finance/greeks/__init__.py
fianchetto_tradebot/common_models/api/finance/greeks/greeks.py
fianchetto_tradebot/common_models/api/orders/__init__.py
fianchetto_tradebot/common_models/api/orders/cancel_order_request.py
fianchetto_tradebot/common_models/api/orders/cancel_order_response.py
fianchetto_tradebot/common_models/api/orders/get_order_request.py
fianchetto_tradebot-0.1.15.dist-info/licenses/LICENSE
fianchetto_tradebot-0.1.15.dist-info/METADATA
fianchetto_tradebot-0.1.15.dist-info/WHEEL
fianchetto_tradebot-0.1.15.dist-info/top_level.txt
fianchetto_tradebot-0.1.15.dist-info/RECORD
