Metadata-Version: 2.4
Name: fianchetto-tradebot
Version: 0.1.15
Summary: An algorithmic trading bot framework connecting to brokerages like E*Trade and Schwab
Author-email: Aleks Shulman <aleks@fianchettolabs.com>
Requires-Python: >=3.6
License-File: LICENSE
Requires-Dist: aioauth-client<1.0,>=0.30
Requires-Dist: annotated-types<1.0,>=0.7
Requires-Dist: anyio<5.0,>=4.9
Requires-Dist: attrs<26.0,>=25.3
Requires-Dist: blinker<2.0,>=1.9
Requires-Dist: certifi<2026.0,>=2025.1
Requires-Dist: charset-normalizer<4.0,>=3.4
Requires-Dist: click<9.0,>=8.1
Requires-Dist: exceptiongroup<2.0,>=1.2
Requires-Dist: fastapi<1.0,>=0.115
Requires-Dist: flasgger<1.0,>=0.9
Requires-Dist: Flask<4.0,>=3.1
Requires-Dist: h11<1.0,>=0.16
Requires-Dist: httpcore<2.0,>=1.0
Requires-Dist: httpx<1.0,>=0.28
Requires-Dist: idna<4.0,>=3.10
Requires-Dist: importlib_metadata<9.0,>=8.6
Requires-Dist: itsdangerous<3.0,>=2.2
Requires-Dist: Jinja2<4.0,>=3.1
Requires-Dist: jsonpickle<5.0,>=4.0
Requires-Dist: jsonschema<5.0,>=4.23
Requires-Dist: jsonschema-specifications<2026.0,>=2025.4
Requires-Dist: MarkupSafe<4.0,>=3.0
Requires-Dist: mistune<4.0,>=3.1
Requires-Dist: numpy<3.0,>=2.0
Requires-Dist: packaging<25.0,>=24.2
Requires-Dist: pandas<3.0,>=2.2
Requires-Dist: pluggy<2.0,>=1.5
Requires-Dist: pydantic<3.0,>=2.11
Requires-Dist: pydantic_core<3.0,>=2.33
Requires-Dist: Pygments<3.0,>=2.19
Requires-Dist: python-dateutil<3.0,>=2.9
Requires-Dist: pytz<2026.0,>=2025.2
Requires-Dist: PyYAML<7.0,>=6.0
Requires-Dist: rauth<1.0,>=0.7
Requires-Dist: referencing<1.0,>=0.36
Requires-Dist: requests<3.0,>=2.32
Requires-Dist: rpds-py<1.0,>=0.24
Requires-Dist: six<2.0,>=1.17
Requires-Dist: sniffio<2.0,>=1.3
Requires-Dist: sortedcontainers<3.0,>=2.4
Requires-Dist: starlette<1.0,>=0.46
Requires-Dist: tomli<3.0,>=2.2
Requires-Dist: typing-inspection<1.0,>=0.4
Requires-Dist: typing_extensions<5.0,>=4.13
Requires-Dist: tzdata<2026.0,>=2025.2
Requires-Dist: urllib3<3.0,>=2.4
Requires-Dist: uvicorn[standard]<1.0,>=0.34
Requires-Dist: Werkzeug<4.0,>=3.1
Requires-Dist: zipp<4.0,>=3.21
Provides-Extra: dev
Requires-Dist: build<2.0,>=1.2; extra == "dev"
Requires-Dist: pyproject_hooks<2.0,>=1.2; extra == "dev"
Requires-Dist: pytest<9.0,>=8.3; extra == "dev"
Dynamic: license-file
